README.md
setup.py
hkzlautoapi.egg-info/PKG-INFO
hkzlautoapi.egg-info/SOURCES.txt
hkzlautoapi.egg-info/dependency_links.txt
hkzlautoapi.egg-info/requires.txt
hkzlautoapi.egg-info/top_level.txt
test_case/__init__.py
util/__init__.py
util/assert_util.py
util/excel_util.py
util/global_var.py
util/json_util.py
util/keyword_function.py
util/log_util.py
util/mongo_util.py
util/mqtt_util.py
util/request_util.py